LICENSE
MANIFEST.in
README.md
setup.cfg
setup.py
pymogilefs/__init__.py
pymogilefs/backend.py
pymogilefs/client.py
pymogilefs/connection.py
pymogilefs/exceptions.py
pymogilefs/request.py
pymogilefs/response.py
pymogilefs.egg-info/PKG-INFO
pymogilefs.egg-info/SOURCES.txt
pymogilefs.egg-info/dependency_links.txt
pymogilefs.egg-info/requires.txt
pymogilefs.egg-info/top_level.txt