Metadata-Version: 1.1
Name: pymogilefs
Version: 0.1.2
Summary: Python MogileFS Client
Home-page: https://github.com/bwind/pymogilefs
Author: Bas Wind
Author-email: mailtobwind@gmail.com
License: MIT
Platform: UNKNOWN
Classifier: Development Status :: 4 - Beta
Classifier: Intended Audience :: Developers
Classifier: License :: OSI Approved :: MIT License
Classifier: Operating System :: OS Independent
Classifier: Programming Language :: Python
Classifier: Topic :: Software Development :: Libraries :: Python Modules
